setup.py
cdep/__init__.py
cdep/configuration/__init__.py
cdep/configuration/drivers/__base.py
cdep/configuration/drivers/__file.py
cdep/configuration/drivers/__file_safe.py
cdep/configuration/drivers/__init__.py
cdep/configuration/functions/__init__.py
cdep/configuration/functions/__load.py
cdep/configuration/functions/__save.py
cdep/configuration/models/__init__.py
cdep/configuration/models/base.py
cdep_package_configuration.egg-info/PKG-INFO
cdep_package_configuration.egg-info/SOURCES.txt
cdep_package_configuration.egg-info/dependency_links.txt
cdep_package_configuration.egg-info/requires.txt
cdep_package_configuration.egg-info/top_level.txt